{
  "hue": 63,
  "padding": {
    "left": 2,
    "right": 2,
    "top": 5,
    "bottom": 5
  },
  "player": {
    "position": {
      "x": -96,
      "y": 72
    }
  },
  "finish": {
    "position": {
      "x": 192,
      "y": 1576
    }
  },
  "objects": [
    {
      "type": "platform",
      "position": {
        "x": -96,
        "y": 32
      },
      "width": 704
    },
    {
      "type": "platform",
      "position": {
        "x": 145.47986,
        "y": 352
      },
      "width": 256,
      "rotation": 12
    },
    {
      "type": "platform",
      "position": {
        "x": -332.86475,
        "y": 641.9945
      },
      "width": 256,
      "rotation": 348
    },
    {
      "type": "platform",
      "position": {
        "x": -455.99994,
        "y": 849.4654
      },
      "width": 1650.9308,
      "rotation": 270
    },
    {
      "type": "platform",
      "position": {
        "x": 264,
        "y": 849.4654
      },
      "width": 1650.9308,
      "rotation": 270
    },
    {
      "type": "platform",
      "position": {
        "x": 143.5276,
        "y": 861.9326
      },
      "width": 252.00815,
      "rotation": 12
    },
    {
      "type": "platform",
      "position": {
        "x": -332.8648,
        "y": 1199.4174
      },
      "width": 256.00012,
      "rotation": 348
    },
    {
      "type": "platform",
      "position": {
        "x": 149.15237,
        "y": 1504
      },
      "width": 213.69516
    },
    {
      "type": "platform",
      "position": {
        "x": -96,
        "y": 1666.9308
      },
      "width": 704
    }
  ]
}